{
  "script": {
    "42434b6c-8694-4bfa-bd01-097c6e08b7ab": {
      "_id": "42434b6c-8694-4bfa-bd01-097c6e08b7ab",
      "context": "SOCIAL_IDP_PROFILE_TRANSFORMATION",
      "createdBy": "null",
      "creationDate": 0,
      "default": false,
      "description": "Normalizes raw profile data from GitHub",
      "evaluatorVersion": "1.0",
      "language": "GROOVY",
      "lastModifiedBy": "null",
      "lastModifiedDate": 0,
      "name": "Okta Profile Normalization - imported (7)",
      "script": "file://Okta-Profile-Normalization-imported-(7).script.groovy"
    }
  }
}
